source_recharge/__init__.py
source_recharge/components/datetime_based_cursor.py
source_recharge/components/recharge_error_handler.py
source_recharge/manifest.yaml
source_recharge/run.py
source_recharge/schemas/addresses.json
source_recharge/schemas/bundle_selections.json
source_recharge/schemas/charges.json
source_recharge/schemas/collections.json
source_recharge/schemas/credit_adjustments.json
source_recharge/schemas/customers.json
source_recharge/schemas/discounts.json
source_recharge/schemas/events.json
source_recharge/schemas/metafields.json
source_recharge/schemas/onetimes.json
source_recharge/schemas/orders.json
source_recharge/schemas/payment_methods.json
source_recharge/schemas/plans.json
source_recharge/schemas/shop.json
source_recharge/schemas/subscriptions.json
source_recharge/source.py
source_recharge/spec.json
source_recharge/streams.py
airbyte_source_recharge-3.0.11.dist-info/METADATA
airbyte_source_recharge-3.0.11.dist-info/WHEEL
airbyte_source_recharge-3.0.11.dist-info/entry_points.txt
airbyte_source_recharge-3.0.11.dist-info/RECORD
