Metadata-Version: 2.1
Name: airbyte-source-recharge
Version: 3.0.11
Summary: Source implementation for Recharge.
Home-page: https://airbyte.com
License: ELv2
Author: Airbyte
Author-email: contact@airbyte.io
Requires-Python: >=3.10,<3.12
Classifier: License :: Other/Proprietary License
Classifier: Programming Language :: Python :: 3
Classifier: Programming Language :: Python :: 3.10
Classifier: Programming Language :: Python :: 3.11
Requires-Dist: airbyte-cdk (>=4,<5)
Requires-Dist: freezegun (>=1.4.0,<2.0.0)
Project-URL: Documentation, https://docs.airbyte.com/integrations/sources/recharge
Project-URL: Repository, https://github.com/airbytehq/airbyte
